drf_around/__init__.py
drf_around/mixins.py
drf_around/permissions.py
drf_around/serializers.py
drf_around/viewsets.py
tests/__init__.py
tests/models.py
tests/serializers.py
tests/settings.py
tests/test_permissions.py
tests/test_serializers.py
tests/urls.py
tests/viewsets.py
drf_around-0.0.3.1.dist-info/LICENSE.md
drf_around-0.0.3.1.dist-info/METADATA
drf_around-0.0.3.1.dist-info/WHEEL
drf_around-0.0.3.1.dist-info/top_level.txt
drf_around-0.0.3.1.dist-info/RECORD
